clisync/__init__.py
clisync/shell.py
clisync/utils.py
clisync-1.3.2.dist-info/LICENSE
clisync-1.3.2.dist-info/METADATA
clisync-1.3.2.dist-info/WHEEL
clisync-1.3.2.dist-info/top_level.txt
clisync-1.3.2.dist-info/RECORD
