Metadata-Version: 2.1
Name: clisync
Version: 1.3.2
Summary: Generate click commands from your project
Home-page: https://clisync.surge.sh
Author: Edward Laurence
Author-email: edwardl@hectiq.ai
Keywords: pip requirements imports
Classifier: Programming Language :: Python :: 3
Classifier: Intended Audience :: Developers
Classifier: Operating System :: OS Independent
Classifier: Topic :: Software Development :: Libraries :: Python Modules
Classifier: Topic :: Scientific/Engineering
Classifier: Intended Audience :: Science/Research
License-File: LICENSE
Requires-Dist: click
